pycomply/__init__.py
pycomply/connection.py
pycomply/constants.py
pycomply/errors.py
pycomply-0.1.12.dist-info/WHEEL
pycomply-0.1.12.dist-info/METADATA
pycomply-0.1.12.dist-info/RECORD
